web.sh-0.1.4.dist-info/DESCRIPTION.rst
web.sh-0.1.4.dist-info/entry_points.txt
web.sh-0.1.4.dist-info/METADATA
web.sh-0.1.4.dist-info/metadata.json
web.sh-0.1.4.dist-info/pbr.json
web.sh-0.1.4.dist-info/RECORD
web.sh-0.1.4.dist-info/top_level.txt
web.sh-0.1.4.dist-info/WHEEL
websh/__init__.py
websh/websh.py
