Metadata-Version: 2.0
Name: web.sh
Version: 0.1.4
Summary: web.sh is a cross-platform script (web) and API for launching a browser(with x-www-browser (Linux, Unix), open (OSX), start (Windows),or python -m webbrowser)
Home-page: https://github.com/westurner/web.sh
Author: Wes Turner
Author-email: wes@wrd.nu
License: BSD
Keywords: websh browser webbrowser x-www-browser
Platform: UNKNOWN
Classifier: Development Status :: 2 - Pre-Alpha
Classifier: Intended Audience :: Developers
Classifier: License :: OSI Approved :: BSD License
Classifier: Natural Language :: English
Classifier: Programming Language :: Python :: 2
Classifier: Programming Language :: Python :: 2.6
Classifier: Programming Language :: Python :: 2.7
Classifier: Programming Language :: Python :: 3
Classifier: Programming Language :: Python :: 3.3
Classifier: Programming Language :: Python :: 3.4
